{"id":"5xps6q691bk9c6wqacaq28b","title":"Docker commands","desc":"","updated":1673709337319,"created":1673423404655,"custom":{},"fname":"docker.docker-commands","type":"note","vault":{"fsPath":"dependencies/localhost/containers","selfContained":true,"name":"containers"},"contentHash":"25e3df5bc036daf02bb343bec8290b71","links":[],"anchors":{"installation":{"type":"header","text":"Installation","value":"installation","line":8,"column":0,"depth":2},"build-images":{"type":"header","text":"Build Images","value":"build-images","line":28,"column":0,"depth":2},"docker-cli":{"type":"header","text":"Docker CLI","value":"docker-cli","line":32,"column":0,"depth":2},"backup-a-container":{"type":"header","text":"Backup a container","value":"backup-a-container","line":132,"column":0,"depth":3},"restore-container-from-backup":{"type":"header","text":"Restore container from backup","value":"restore-container-from-backup","line":137,"column":0,"depth":3},"networks":{"type":"header","text":"Networks","value":"networks","line":142,"column":0,"depth":2},"troubleshooting":{"type":"header","text":"Troubleshooting","value":"troubleshooting","line":144,"column":0,"depth":2},"networking":{"type":"header","text":"Networking","value":"networking","line":146,"column":0,"depth":3}},"children":[],"parent":"awxx3cehszyb4datrqlycg2","data":{}}
